django_admin_hotkeys/__init__.py
django_admin_hotkeys/apps.py
django_admin_hotkeys/static/django_admin_hotkeys/search_form.js
django_admin_hotkeys/templates/admin/change_list.html
django_admin_hotkeys-0.1.1.dist-info/licenses/LICENSE
django_admin_hotkeys-0.1.1.dist-info/METADATA
django_admin_hotkeys-0.1.1.dist-info/WHEEL
django_admin_hotkeys-0.1.1.dist-info/top_level.txt
django_admin_hotkeys-0.1.1.dist-info/RECORD
