Metadata-Version: 2.4
Name: django-admin-hotkeys
Version: 0.1.1
Summary: Add hotkeys to the Django admin interface to improve your workflow
Author-email: amureki <oss@amureki.me>
License-Expression: BSD-2-Clause
Project-URL: Homepage, https://github.com/amureki/django-admin-hotkeys
Project-URL: Issues, https://github.com/amureki/django-admin-hotkeys/issues
Keywords: Django
Classifier: Development Status :: 4 - Beta
Classifier: Environment :: Web Environment
Classifier: Framework :: Django
Classifier: Framework :: Django :: 4.2
Classifier: Framework :: Django :: 5.1
Classifier: Framework :: Django :: 5.2
Classifier: Intended Audience :: Developers
Classifier: Natural Language :: English
Classifier: Operating System :: OS Independent
Classifier: Programming Language :: Python :: 3 :: Only
Classifier: Programming Language :: Python :: 3.9
Classifier: Programming Language :: Python :: 3.10
Classifier: Programming Language :: Python :: 3.11
Classifier: Programming Language :: Python :: 3.12
Classifier: Programming Language :: Python :: 3.13
Requires-Python: >=3.9
License-File: LICENSE
Requires-Dist: django>=4.2
Dynamic: license-file
